snpvclient/__init__.py
snpvclient/actions.py
snpvclient/api.py
snpvclient/client.py
snpvclient/exceptions.py
snpvclient/utils.py
snpvclient/working.py
snpvclient/__pycache__/__init__.cpython-312.pyc
snpvclient/__pycache__/actions.cpython-312.pyc
snpvclient/__pycache__/api.cpython-312.pyc
snpvclient/__pycache__/client.cpython-312.pyc
snpvclient/__pycache__/exceptions.cpython-312.pyc
snpvclient/__pycache__/utils.cpython-312.pyc
snpvclient-0.1.6.dist-info/licenses/LICENSE
snpvclient-0.1.6.dist-info/METADATA
snpvclient-0.1.6.dist-info/WHEEL
snpvclient-0.1.6.dist-info/top_level.txt
snpvclient-0.1.6.dist-info/RECORD
