Metadata-Version: 2.4
Name: snpvclient
Version: 0.1.6
Summary: A Python client for connecting to a Supernote Private Cloud Instance.
Author-email: André Costa <andre@dphacks.com>
License:                     GNU GENERAL PUBLIC LICENSE
Project-URL: Homepage, https://github.com/camerahacks/sn-private-client/
Keywords: Supernote,Ratta,Private,Cloud
Requires-Python: >=3.10
License-File: LICENSE
Requires-Dist: requests>=2.32.5
Requires-Dist: python-dotenv
Dynamic: license-file
